wavestate/declarative/__init__.py
wavestate/declarative/_version.py
wavestate/declarative/metaclass.py
wavestate/declarative/overridable_object.py
wavestate/declarative/run.py
wavestate/declarative/argparse/__init__.py
wavestate/declarative/argparse/annotations.py
wavestate/declarative/argparse/oo_argparse.py
wavestate/declarative/callbacks/__init__.py
wavestate/declarative/callbacks/callbacks.py
wavestate/declarative/callbacks/relay.py
wavestate/declarative/callbacks/state_booleans.py
wavestate/declarative/callbacks/validators.py
wavestate/declarative/properties/__init__.py
wavestate/declarative/properties/bases.py
wavestate/declarative/properties/memoized.py
wavestate/declarative/properties/memoized_adv.py
wavestate/declarative/properties/memoized_adv_group.py
wavestate/declarative/properties/utilities.py
wavestate/declarative/utilities/__init__.py
wavestate/declarative/utilities/representations.py
wavestate/declarative/utilities/super_base.py
wavestate/declarative/utilities/unique.py
wavestate.declarative-1.3.4.dist-info/METADATA
wavestate.declarative-1.3.4.dist-info/NOTICE
wavestate.declarative-1.3.4.dist-info/WHEEL
wavestate.declarative-1.3.4.dist-info/top_level.txt
wavestate.declarative-1.3.4.dist-info/RECORD
