Metadata-Version: 2.1
Name: wavestate.declarative
Version: 1.3.4
Summary: Base classes and methods for declarative object instantiation
Home-page: https://github.com/wavestate/wavestate-declarative
Author: Lee McCuller
Author-email: mcculler@mit.edu
License: Apache-2.0
Project-URL: Bug Tracker, https://github.com/wavestate/wavestate-declarative/issues
Project-URL: Source Code, https://github.com/wavestate/wavestate-declarative
Platform: UNKNOWN
Classifier: Intended Audience :: Science/Research
Classifier: License :: OSI Approved :: Apache Software License
Classifier: Operating System :: OS Independent
Classifier: Programming Language :: Python
Classifier: Programming Language :: Python :: 3
Classifier: Topic :: Scientific/Engineering :: Physics
License-File: LICENSES/Apache-2.0.txt
License-File: LICENSES/CC0-1.0.txt
License-File: NOTICE
Requires-Dist: setuptools-scm (>=6.0.0)
